{
	"configurations" : 
	[
		{
			"abstractTargets" : [],
			"directories" : 
			[
				{
					"build" : ".",
					"jsonFile" : "directory-.-Debug-f040eec181a89de70dbe.json",
					"minimumCMakeVersion" : 
					{
						"string" : "4.2"
					},
					"projectIndex" : 0,
					"source" : ".",
					"targetIndexes" : 
					[
						0,
						1,
						2
					]
				}
			],
			"name" : "Debug",
			"projects" : 
			[
				{
					"directoryIndexes" : 
					[
						0
					],
					"name" : "CXX_List_vs_BST_vs_AVL",
					"targetIndexes" : 
					[
						0,
						1,
						2
					]
				}
			],
			"targets" : 
			[
				{
					"directoryIndex" : 0,
					"id" : "ALL_BUILD::@6890427a1f51a3e7e1df",
					"jsonFile" : "target-ALL_BUILD-Debug-aec1630a85a2629ade02.json",
					"name" : "ALL_BUILD",
					"projectIndex" : 0
				},
				{
					"directoryIndex" : 0,
					"id" : "CXX_List_vs_BST_vs_AVL::@6890427a1f51a3e7e1df",
					"jsonFile" : "target-CXX_List_vs_BST_vs_AVL-Debug-7a841ac441a7786662f7.json",
					"name" : "CXX_List_vs_BST_vs_AVL",
					"projectIndex" : 0
				},
				{
					"directoryIndex" : 0,
					"id" : "ZERO_CHECK::@6890427a1f51a3e7e1df",
					"jsonFile" : "target-ZERO_CHECK-Debug-45f4a99a31ba6e73c26c.json",
					"name" : "ZERO_CHECK",
					"projectIndex" : 0
				}
			]
		},
		{
			"abstractTargets" : [],
			"directories" : 
			[
				{
					"build" : ".",
					"jsonFile" : "directory-.-Release-f040eec181a89de70dbe.json",
					"minimumCMakeVersion" : 
					{
						"string" : "4.2"
					},
					"projectIndex" : 0,
					"source" : ".",
					"targetIndexes" : 
					[
						0,
						1,
						2
					]
				}
			],
			"name" : "Release",
			"projects" : 
			[
				{
					"directoryIndexes" : 
					[
						0
					],
					"name" : "CXX_List_vs_BST_vs_AVL",
					"targetIndexes" : 
					[
						0,
						1,
						2
					]
				}
			],
			"targets" : 
			[
				{
					"directoryIndex" : 0,
					"id" : "ALL_BUILD::@6890427a1f51a3e7e1df",
					"jsonFile" : "target-ALL_BUILD-Release-aec1630a85a2629ade02.json",
					"name" : "ALL_BUILD",
					"projectIndex" : 0
				},
				{
					"directoryIndex" : 0,
					"id" : "CXX_List_vs_BST_vs_AVL::@6890427a1f51a3e7e1df",
					"jsonFile" : "target-CXX_List_vs_BST_vs_AVL-Release-b8abccd4dd318bbb06b0.json",
					"name" : "CXX_List_vs_BST_vs_AVL",
					"projectIndex" : 0
				},
				{
					"directoryIndex" : 0,
					"id" : "ZERO_CHECK::@6890427a1f51a3e7e1df",
					"jsonFile" : "target-ZERO_CHECK-Release-45f4a99a31ba6e73c26c.json",
					"name" : "ZERO_CHECK",
					"projectIndex" : 0
				}
			]
		},
		{
			"abstractTargets" : [],
			"directories" : 
			[
				{
					"build" : ".",
					"jsonFile" : "directory-.-MinSizeRel-f040eec181a89de70dbe.json",
					"minimumCMakeVersion" : 
					{
						"string" : "4.2"
					},
					"projectIndex" : 0,
					"source" : ".",
					"targetIndexes" : 
					[
						0,
						1,
						2
					]
				}
			],
			"name" : "MinSizeRel",
			"projects" : 
			[
				{
					"directoryIndexes" : 
					[
						0
					],
					"name" : "CXX_List_vs_BST_vs_AVL",
					"targetIndexes" : 
					[
						0,
						1,
						2
					]
				}
			],
			"targets" : 
			[
				{
					"directoryIndex" : 0,
					"id" : "ALL_BUILD::@6890427a1f51a3e7e1df",
					"jsonFile" : "target-ALL_BUILD-MinSizeRel-aec1630a85a2629ade02.json",
					"name" : "ALL_BUILD",
					"projectIndex" : 0
				},
				{
					"directoryIndex" : 0,
					"id" : "CXX_List_vs_BST_vs_AVL::@6890427a1f51a3e7e1df",
					"jsonFile" : "target-CXX_List_vs_BST_vs_AVL-MinSizeRel-4a89a11fad2f815e7650.json",
					"name" : "CXX_List_vs_BST_vs_AVL",
					"projectIndex" : 0
				},
				{
					"directoryIndex" : 0,
					"id" : "ZERO_CHECK::@6890427a1f51a3e7e1df",
					"jsonFile" : "target-ZERO_CHECK-MinSizeRel-45f4a99a31ba6e73c26c.json",
					"name" : "ZERO_CHECK",
					"projectIndex" : 0
				}
			]
		},
		{
			"abstractTargets" : [],
			"directories" : 
			[
				{
					"build" : ".",
					"jsonFile" : "directory-.-RelWithDebInfo-f040eec181a89de70dbe.json",
					"minimumCMakeVersion" : 
					{
						"string" : "4.2"
					},
					"projectIndex" : 0,
					"source" : ".",
					"targetIndexes" : 
					[
						0,
						1,
						2
					]
				}
			],
			"name" : "RelWithDebInfo",
			"projects" : 
			[
				{
					"directoryIndexes" : 
					[
						0
					],
					"name" : "CXX_List_vs_BST_vs_AVL",
					"targetIndexes" : 
					[
						0,
						1,
						2
					]
				}
			],
			"targets" : 
			[
				{
					"directoryIndex" : 0,
					"id" : "ALL_BUILD::@6890427a1f51a3e7e1df",
					"jsonFile" : "target-ALL_BUILD-RelWithDebInfo-aec1630a85a2629ade02.json",
					"name" : "ALL_BUILD",
					"projectIndex" : 0
				},
				{
					"directoryIndex" : 0,
					"id" : "CXX_List_vs_BST_vs_AVL::@6890427a1f51a3e7e1df",
					"jsonFile" : "target-CXX_List_vs_BST_vs_AVL-RelWithDebInfo-f5edf0990b288fd9cd7f.json",
					"name" : "CXX_List_vs_BST_vs_AVL",
					"projectIndex" : 0
				},
				{
					"directoryIndex" : 0,
					"id" : "ZERO_CHECK::@6890427a1f51a3e7e1df",
					"jsonFile" : "target-ZERO_CHECK-RelWithDebInfo-45f4a99a31ba6e73c26c.json",
					"name" : "ZERO_CHECK",
					"projectIndex" : 0
				}
			]
		}
	],
	"kind" : "codemodel",
	"paths" : 
	{
		"build" : "C:/Users/aegan/Documents/GitHub/CXX_List_vs_BST_vs_AVL/build",
		"source" : "C:/Users/aegan/Documents/GitHub/CXX_List_vs_BST_vs_AVL"
	},
	"version" : 
	{
		"major" : 2,
		"minor" : 10
	}
}
